tests/__init__.py
tests/test_pebbles.py
tests/data/generate_test_sam.sh
tests/data/map.bam
tests/data/map.sam
tests/data/query.fa
tests/data/ref.fa
pebbles/__init__.py
pebbles/countess.py
pebbles/pebbles.py
pebbles-0.3.0.dist-info/METADATA
pebbles-0.3.0.dist-info/WHEEL
pebbles-0.3.0.dist-info/entry_points.txt
pebbles-0.3.0.dist-info/RECORD
