Metadata-Version: 2.1
Name: pebbles
Version: 0.3.0
Summary: A package for calling HGVS variants in single SAM/BAM alignments
Project-URL: Homepage, https://github.com/genomematt/pebbles
Project-URL: Bug Tracker, https://github.com/genomematt/pebbles
Author-email: Matthew Wakefield <matthew.wakefield@unimelb.edu.au>
Classifier: Development Status :: 4 - Beta
Classifier: Intended Audience :: Science/Research
Classifier: License :: OSI Approved :: BSD License
Classifier: Operating System :: OS Independent
Classifier: Programming Language :: Python :: 3
Classifier: Topic :: Scientific/Engineering :: Bio-Informatics
Requires-Python: >=3.9
Requires-Dist: pysam>=0.20.0
Provides-Extra: countess
Requires-Dist: countess<0.1,>=0.0.24; extra == 'countess'
